{
  "main": {
    "id": "7bdee42ccbc652a5",
    "type": "split",
    "children": [
      {
        "id": "a195a9f7e534295b",
        "type": "tabs",
        "children": [
          {
            "id": "1e42142ce7202a9a",
            "type": "leaf",
            "state": {
              "type": "markdown",
              "state": {
                "file": "_posts/2024-5-16-Obsidian正文使用思源宋体.md",
                "mode": "source",
                "source": false
              }
            }
          }
        ]
      }
    ],
    "direction": "vertical"
  },
  "left": {
    "id": "bd59279fd5442fb4",
    "type": "mobile-drawer",
    "children": [
      {
        "id": "d188dfc2061807d7",
        "type": "leaf",
        "state": {
          "type": "file-explorer",
          "state": {
            "sortOrder": "alphabeticalReverse"
          }
        }
      },
      {
        "id": "1b0053011cc4605b",
        "type": "leaf",
        "state": {
          "type": "search",
          "state": {
            "query": "",
            "matchingCase": false,
            "explainSearch": false,
            "collapseAll": false,
            "extraContext": false,
            "sortOrder": "alphabetical"
          }
        }
      },
      {
        "id": "8e69f86942342444",
        "type": "leaf",
        "state": {
          "type": "tag",
          "state": {
            "sortOrder": "frequency",
            "useHierarchy": true
          }
        }
      },
      {
        "id": "1ffc2674e295343b",
        "type": "leaf",
        "state": {
          "type": "bookmarks",
          "state": {}
        }
      }
    ],
    "currentTab": 0
  },
  "right": {
    "id": "fedb812f9b5d97ed",
    "type": "mobile-drawer",
    "children": [
      {
        "id": "bd442858d709aeaf",
        "type": "leaf",
        "state": {
          "type": "backlink",
          "state": {
            "file": "_posts/2024-5-16-Obsidian正文使用思源宋体.md",
            "collapseAll": false,
            "extraContext": false,
            "sortOrder": "alphabetical",
            "showSearch": false,
            "searchQuery": "",
            "backlinkCollapsed": false,
            "unlinkedCollapsed": true
          }
        }
      },
      {
        "id": "0e7995c5ee9b5396",
        "type": "leaf",
        "state": {
          "type": "outgoing-link",
          "state": {
            "file": "_posts/2024-5-16-Obsidian正文使用思源宋体.md",
            "linksCollapsed": false,
            "unlinkedCollapsed": true
          }
        }
      },
      {
        "id": "b2747bc8ff2f11f8",
        "type": "leaf",
        "state": {
          "type": "outline",
          "state": {
            "file": "_posts/2024-5-16-Obsidian正文使用思源宋体.md"
          }
        }
      }
    ],
    "currentTab": 0
  },
  "left-ribbon": {
    "hiddenItems": {
      "cmdr:Obsidian Git: Commit all changes": false,
      "cmdr:Obsidian Git: Push": false,
      "cmdr:Linter: 格式化当前文件": false,
      "switcher:打开快速切换": false,
      "graph:查看关系图谱": false,
      "canvas:新建白板": false,
      "daily-notes:打开/创建今天的日记": false,
      "templates:插入模板": false,
      "command-palette:打开命令面板": false
    }
  },
  "active": "d188dfc2061807d7",
  "lastOpenFiles": [
    "_posts/2024-5-16-Obsidian正文使用思源宋体.md",
    "_posts/2024-4-30-中年改命最高明的方法，就两个字.md",
    "_posts/2024-5-10-IDM-Activation-Script.md",
    "_posts/2024-4-30-中年改命最高明的方法.md",
    "/_posts/2024-5-16-Obsidian正文使用思源宋体代码.md",
    "/_posts/2024-5-10-IDM-Activation-Script.md",
    "/_posts/2024-4-30-中年改命最高明的方法.md",
    "_posts/2024-4-26-Github问题汇集.md",
    "/_posts/2024-4-30-中年改命最高明的方法，就两个字.md",
    "/css/hux-blog.min.css",
    "/_posts/2024-4-26-Github问题汇集.md",
    "/_posts/2024-4-22-中国式饭局的真相.md",
    "_posts/2024-3-21-在延安文艺座谈会上的讲话.md",
    "_posts/2024-4-22-中国式饭局的真相.md",
    "/_includes/about/zh.md",
    "_posts/2024-3-21-邦国同志是如何抓住牛鼻子？.md",
    "_posts/2024-3-19-湖南农民运动考察报告.md",
    "/_posts/2024-3-21-邦国同志是如何抓住牛鼻子？.md",
    "/_posts/2024-3-21-在延安文艺座谈会上的讲话.md",
    "/_posts/2024-3-19-湖南农民运动考察报告.md",
    "_posts/2024-3-18-新华社：告别过去，珍惜当下.md",
    "_posts/2024-3-7-历险罗纹河.md",
    "_posts/未命名.md",
    "/_posts/2024-3-18-新华社：告别过去，珍惜当下.md",
    "_posts/2024-2-13-锅巴往事.md",
    "_posts/2024-2-14-免费图床.md",
    "_posts/2023-12-14-秋日回乡偶记.md",
    "img/in-post/post-alitrip-pd/post-alitrip-pd.029.jpg",
    "img/in-post/post-f-f-weibo.png",
    "less/mixins.less",
    "js/jquery.min.js",
    "fonts/glyphicons-halflings-regular.eot",
    "img/in-post/post-nextgen-web-pwa/qcon-trend.png",
    "_doc",
    "js/hux-blog.min.js",
    "img/in-post/post-kuaidi-1.jpg",
    "img/bg-me-2022.jpg",
    "_includes/about",
    "img/in-post/post-eleme-pwa/before-skeleton.jpg",
    "js/bootstrap.min.js",
    "img/post-bg-4.jpg",
    "img/in-post/post-alitrip-pd/post-alitrip-pd.014.jpg",
    "img/in-post/post-eleme-pwa/PRECACHE-future-routes.jpg",
    "Rakefile",
    "img/post-bg-xx.jpg",
    "_includes/head.html"
  ]
}